odoo8_addon_help_popup-8.0.0.5.0.99.dev17-py2.7-nspkg.pth
odoo8_addon_help_popup-8.0.0.5.0.99.dev17.dist-info/METADATA
odoo8_addon_help_popup-8.0.0.5.0.99.dev17.dist-info/RECORD
odoo8_addon_help_popup-8.0.0.5.0.99.dev17.dist-info/WHEEL
odoo8_addon_help_popup-8.0.0.5.0.99.dev17.dist-info/namespace_packages.txt
odoo8_addon_help_popup-8.0.0.5.0.99.dev17.dist-info/top_level.txt
odoo_addons/help_popup/README.rst
odoo_addons/help_popup/__init__.py
odoo_addons/help_popup/__openerp__.py
odoo_addons/help_popup/model.py
odoo_addons/help_popup/demo/help.xml
odoo_addons/help_popup/i18n/ar.po
odoo_addons/help_popup/i18n/de.po
odoo_addons/help_popup/i18n/es.po
odoo_addons/help_popup/i18n/eu.po
odoo_addons/help_popup/i18n/fi.po
odoo_addons/help_popup/i18n/fr.po
odoo_addons/help_popup/i18n/help_popup.pot
odoo_addons/help_popup/i18n/it.po
odoo_addons/help_popup/i18n/pt_BR.po
odoo_addons/help_popup/i18n/sl.po
odoo_addons/help_popup/i18n/tr.po
odoo_addons/help_popup/report/help.xml
odoo_addons/help_popup/report/report.xml
odoo_addons/help_popup/static/description/icon.png
odoo_addons/help_popup/static/description/popup.png
odoo_addons/help_popup/static/src/js/popup_help.js
odoo_addons/help_popup/static/src/xml/popup_help.xml
odoo_addons/help_popup/views/action_view.xml
odoo_addons/help_popup/views/popup_help_view.xml
